{"dataset_id": 1186, "name": "BNG(eucalyptus)", "version": 1, "description": null, "creator": ["Geoffrey Holmes", "Bernhard Pfahringer", "Jan van Rijn", "Joaquin Vanschoren"], "contributor": null, "collection_date": "2014-11-12 12:19:01", "upload_date": "2014-11-12T12:19:08", "language": null, "license": "public domain", "default_target_attribute": "Utility", "row_id_attribute": null, "ignore_attribute": null, "tags": ["artificial", "BNG"], "features": [{"index": 0, "name": "Abbrev", "data_type": "nominal", "nominal_values": ["Cra", "Cly", "Nga", "Wai", "K81", "Wak", "K82", "WSp", "K83", "Lon", "Puk", "Paw", "K81a", "Mor", "Wen", "WSh"], "number_missing_values": 0}, {"index": 1, "name": "Rep", "data_type": "numeric", "nominal_values": null, "number_missing_values": 0}, {"index": 2, "name": "Locality", "data_type": "nominal", "nominal_values": ["Central_Hawkes_Bay", "Northern_Hawkes_Bay", "Southern_Hawkes_Bay", "Central_Hawkes_Bay_(coastal)", "Central_Wairarapa", "South_Wairarapa", "Southern_Hawkes_Bay_(coastal)", "Central_Poverty_Bay"], "number_missing_values": 0}, {"index": 3, "name": "Map_Ref", "data_type": "nominal", "nominal_values": ["N135_382/137", "N116_848/985", "N145_874/586", "N142_377/957", "N158_344/626", "N162_081/300", "N158_343/625", "N151_912/221", "N162_097/424", "N166_063/197", "N146_273/737", "N141_295/063", "N98_539/567", "N151_922/226"], "number_missing_values": 0}, {"index": 4, "name": "Latitude", "data_type": "nominal", "nominal_values": ["39__38", "39__00", "40__11", "39__50", "40__57", "41__12", "40__36", "41__08", "41__16", "40__00", "39__43", "82__32"], "number_missing_values": 0}, {"index": 5, "name": "Altitude", "data_type": "numeric", "nominal_values": null, "number_missing_values": 0}, {"index": 6, "name": "Rainfall", "data_type": "numeric", "nominal_values": null, "number_missing_values": 0}, {"index": 7, "name": "Frosts", "data_type": "numeric", "nominal_values": null, "number_missing_values": 0}, {"index": 8, "name": "Year", "data_type": "numeric", "nominal_values": null, "number_missing_values": 0}, {"index": 9, "name": "Sp", "data_type": "nominal", "nominal_values": ["co", "fr", "ma", "nd", "ni", "ob", "ov", "pu", "rd", "si", "mn", "ag", "bxs", "br", "el", "fa", "jo", "ka", "re", "sm", "ro", "nc", "am", "cr", "pa", "ra", "te"], "number_missing_values": 0}, {"index": 10, "name": "PMCno", "data_type": "numeric", "nominal_values": null, "number_missing_values": 0}, {"index": 11, "name": "DBH", "data_type": "numeric", "nominal_values": null, "number_missing_values": 0}, {"index": 12, "name": "Ht", "data_type": "numeric", "nominal_values": null, "number_missing_values": 0}, {"index": 13, "name": "Surv", "data_type": "numeric", "nominal_values": null, "number_missing_values": 0}, {"index": 14, "name": "Vig", "data_type": "numeric", "nominal_values": null, "number_missing_values": 0}, {"index": 15, "name": "Ins_res", "data_type": "numeric", "nominal_values": null, "number_missing_values": 0}, {"index": 16, "name": "Stem_Fm", "data_type": "numeric", "nominal_values": null, "number_missing_values": 0}, {"index": 17, "name": "Crown_Fm", "data_type": "numeric", "nominal_values": null, "number_missing_values": 0}, {"index": 18, "name": "Brnch_Fm", "data_type": "numeric", "nominal_values": null, "number_missing_values": 0}, {"index": 19, "name": "Utility", "data_type": "nominal", "nominal_values": ["none", "low", "average", "good", "best"], "number_missing_values": 0}], "qualities": {"AutoCorrelation": 0.21718221718221717, "CfsSubsetEval_DecisionStumpAUC": 0.7499849656328538, "CfsSubsetEval_DecisionStumpErrRate": 0.450698, "CfsSubsetEval_DecisionStumpKappa": 0.4201772434304818, "CfsSubsetEval_NaiveBayesAUC": 0.7499849656328538, "CfsSubsetEval_NaiveBayesErrRate": 0.450698, "CfsSubsetEval_NaiveBayesKappa": 0.4201772434304818, "CfsSubsetEval_kNN1NAUC": 0.7499849656328538, "CfsSubsetEval_kNN1NErrRate": 0.450698, "CfsSubsetEval_kNN1NKappa": 0.4201772434304818, "ClassEntropy": 2.2625670762471075, "DecisionStumpAUC": 0.5801926356418649, "DecisionStumpErrRate": 0.628099, "DecisionStumpKappa": 0.12033318064247978, "Dimensionality": 2e-05, "EquivalentNumberOfAtts": 10.969571232137756, "J48.00001.AUC": 0.8097980244153212, "J48.00001.ErrRate": 0.366658, "J48.00001.Kappa": 0.5294392813678259, "J48.0001.AUC": 0.8097980244153212, "J48.0001.ErrRate": 0.366658, "J48.0001.Kappa": 0.5294392813678259, "J48.001.AUC": 0.8097980244153212, "J48.001.ErrRate": 0.366658, "J48.001.Kappa": 0.5294392813678259, "MajorityClassPercentage": 28.9779, "MajorityClassSize": 289779.0, "MaxAttributeEntropy": 4.553149436774487, "MaxKurtosisOfNumericAtts": 111.65053074193979, "MaxMeansOfNumericAtts": 2071.695980103977, "MaxMutualInformation": 0.3643539323399, "MaxNominalAttDistinctValues": 27.0, "MaxSkewnessOfNumericAtts": 9.103682754860348, "MaxStdDevOfNumericAtts": 1576.0018620137282, "MeanAttributeEntropy": 3.66059075017926, "MeanKurtosisOfNumericAtts": 8.462974047516791, "MeanMeansOfNumericAtts": 391.6815459870233, "MeanMutualInformation": 0.20625847887458199, "MeanNoiseToSignalRatio": 16.747589190770324, "MeanNominalAttDistinctValues": 13.666666666666666, "MeanSkewnessOfNumericAtts": 0.6871254117511135, "MeanStdDevOfNumericAtts": 175.46998249314854, "MinAttributeEntropy": 2.7707320908084156, "MinKurtosisOfNumericAtts": -1.9570521250741162, "MinMeansOfNumericAtts": -2.551536000000001, "MinMutualInformation": 0.1365920732049, "MinNominalAttDistinctValues": 5.0, "MinSkewnessOfNumericAtts": -0.5977650528220442, "MinStdDevOfNumericAtts": 0.4973371975306754, "MinorityClassPercentage": 14.2795, "MinorityClassSize": 142795.0, "NaiveBayesAUC": 0.8189132231557016, "NaiveBayesErrRate": 0.486824, "NaiveBayesKappa": 0.3840384919353702, "NumberOfBinaryFeatures": 0.0, "NumberOfClasses": 5.0, "NumberOfFeatures": 20.0, "NumberOfInstances": 1000000.0, "NumberOfInstancesWithMissingValues": 0.0, "NumberOfMissingValues": 0.0, "NumberOfNumericFeatures": 14.0, "NumberOfSymbolicFeatures": 6.0, "PercentageOfBinaryFeatures": 0.0, "PercentageOfInstancesWithMissingValues": 0.0, "PercentageOfMissingValues": 0.0, "PercentageOfNumericFeatures": 70.0, "PercentageOfSymbolicFeatures": 30.0, "Quartile1AttributeEntropy": 3.139924639951775, "Quartile1KurtosisOfNumericAtts": -0.7351456057228076, "Quartile1MeansOfNumericAtts": 2.920877330086249, "Quartile1MutualInformation": 0.140013983267175, "Quartile1SkewnessOfNumericAtts": -0.3963740089277152, "Quartile1StdDevOfNumericAtts": 0.7863880820834895, "Quartile2AttributeEntropy": 3.6613043437610493, "Quartile2KurtosisOfNumericAtts": -0.18132741801471663, "Quartile2MeansOfNumericAtts": 6.131136814295999, "Quartile2MutualInformation": 0.16554956709366, "Quartile2SkewnessOfNumericAtts": 0.034959664448994676, "Quartile2StdDevOfNumericAtts": 1.796070837527948, "Quartile3AttributeEntropy": 4.180900063615851, "Quartile3KurtosisOfNumericAtts": 0.35770110848768544, "Quartile3MeansOfNumericAtts": 402.3597820759122, "Quartile3MutualInformation": 0.29285743037245, "Quartile3SkewnessOfNumericAtts": 0.6428308160909719, "Quartile3StdDevOfNumericAtts": 84.71702211301597, "REPTreeDepth1AUC": 0.8457068585246161, "REPTreeDepth1ErrRate": 0.398568, "REPTreeDepth1Kappa": 0.4864612913481807, "REPTreeDepth2AUC": 0.8457068585246161, "REPTreeDepth2ErrRate": 0.398568, "REPTreeDepth2Kappa": 0.4864612913481807, "REPTreeDepth3AUC": 0.8457068585246161, "REPTreeDepth3ErrRate": 0.398568, "REPTreeDepth3Kappa": 0.4864612913481807, "RandomTreeDepth1AUC": 0.7157790037802535, "RandomTreeDepth1ErrRate": 0.466568, "RandomTreeDepth1Kappa": 0.40356367876431065, "RandomTreeDepth2AUC": 0.7157790037802535, "RandomTreeDepth2ErrRate": 0.466568, "RandomTreeDepth2Kappa": 0.40356367876431065, "RandomTreeDepth3AUC": 0.7157790037802535, "RandomTreeDepth3ErrRate": 0.466568, "RandomTreeDepth3Kappa": 0.40356367876431065, "StdvNominalAttDistinctValues": 7.659416862050705, "kNN1NAUC": 0.6871911490501941, "kNN1NErrRate": 0.4927, "kNN1NKappa": 0.36896012965471664}}