{"dataset_id": 42139, "name": "public_procurement", "version": 5, "description": "Public procurement data\nfor the European Economic Area, Switzerland, and the\nMacedonia. 2015", "creator": "European Union open data", "contributor": null, "collection_date": "2016-04-18", "upload_date": "2019-09-13T17:23:37", "language": "English", "license": "Public Domain (CC0)", "default_target_attribute": "award_value_euro", "row_id_attribute": null, "ignore_attribute": null, "tags": null, "features": [{"index": 0, "name": "id_notice_can", "data_type": "numeric", "nominal_values": null, "number_missing_values": 0}, {"index": 1, "name": "ted_notice_url", "data_type": "string", "nominal_values": null, "number_missing_values": 0}, {"index": 2, "name": "year", "data_type": "numeric", "nominal_values": null, "number_missing_values": 0}, {"index": 3, "name": "id_type", "data_type": "numeric", "nominal_values": null, "number_missing_values": 0}, {"index": 4, "name": "dt_dispatch", "data_type": "string", "nominal_values": null, "number_missing_values": 0}, {"index": 5, "name": "xsd_version", "data_type": "string", "nominal_values": null, "number_missing_values": 0}, {"index": 6, "name": "cancelled", "data_type": "numeric", "nominal_values": null, "number_missing_values": 0}, {"index": 7, "name": "corrections", "data_type": "numeric", "nominal_values": null, "number_missing_values": 0}, {"index": 8, "name": "b_multiple_cae", "data_type": "string", "nominal_values": null, "number_missing_values": 564949}, {"index": 9, "name": "cae_name", "data_type": "string", "nominal_values": null, "number_missing_values": 0}, {"index": 10, "name": "cae_nationalid", "data_type": "string", "nominal_values": null, "number_missing_values": 468391}, {"index": 11, "name": "cae_address", "data_type": "string", "nominal_values": null, "number_missing_values": 4870}, {"index": 12, "name": "cae_town", "data_type": "string", "nominal_values": null, "number_missing_values": 0}, {"index": 13, "name": "cae_postal_code", "data_type": "string", "nominal_values": null, "number_missing_values": 3181}, {"index": 14, "name": "cae_gpa_annex", "data_type": "string", "nominal_values": null, "number_missing_values": 0}, {"index": 15, "name": "iso_country_code", "data_type": "string", "nominal_values": null, "number_missing_values": 0}, {"index": 16, "name": "iso_country_code_gpa", "data_type": "string", "nominal_values": null, "number_missing_values": 0}, {"index": 17, "name": "b_multiple_country", "data_type": "string", "nominal_values": null, "number_missing_values": 564949}, {"index": 18, "name": "iso_country_code_all", "data_type": "numeric", "nominal_values": null, "number_missing_values": 565163}, {"index": 19, "name": "cae_type", "data_type": "string", "nominal_values": null, "number_missing_values": 0}, {"index": 20, "name": "eu_inst_code", "data_type": "string", "nominal_values": null, "number_missing_values": 562056}, {"index": 21, "name": "main_activity", "data_type": "string", "nominal_values": null, "number_missing_values": 0}, {"index": 22, "name": "b_on_behalf", "data_type": "string", "nominal_values": null, "number_missing_values": 87627}, {"index": 23, "name": "b_involves_joint_procurement", "data_type": "string", "nominal_values": null, "number_missing_values": 564949}, {"index": 24, "name": "b_awarded_by_central_body", "data_type": "string", "nominal_values": null, "number_missing_values": 564949}, {"index": 25, "name": "type_of_contract", "data_type": "string", "nominal_values": null, "number_missing_values": 0}, {"index": 26, "name": "tal_location_nuts", "data_type": "string", "nominal_values": null, "number_missing_values": 180220}, {"index": 27, "name": "b_fra_agreement", "data_type": "string", "nominal_values": null, "number_missing_values": 9}, {"index": 28, "name": "fra_estimated", "data_type": "string", "nominal_values": null, "number_missing_values": 511169}, {"index": 29, "name": "b_fra_contract", "data_type": "string", "nominal_values": null, "number_missing_values": 425621}, {"index": 30, "name": "b_dyn_purch_syst", "data_type": "string", "nominal_values": null, "number_missing_values": 561104}, {"index": 31, "name": "cpv", "data_type": "numeric", "nominal_values": null, "number_missing_values": 0}, {"index": 32, "name": "main_cpv_code_gpa", "data_type": "numeric", "nominal_values": null, "number_missing_values": 0}, {"index": 33, "name": "id_lot", "data_type": "numeric", "nominal_values": null, "number_missing_values": 565012}, {"index": 34, "name": "additional_cpvs", "data_type": "string", "nominal_values": null, "number_missing_values": 345764}, {"index": 35, "name": "b_gpa", "data_type": "string", "nominal_values": null, "number_missing_values": 120026}, {"index": 36, "name": "gpa_coverage", "data_type": "numeric", "nominal_values": null, "number_missing_values": 0}, {"index": 37, "name": "lots_number", "data_type": "numeric", "nominal_values": null, "number_missing_values": 0}, {"index": 38, "name": "value_euro", "data_type": "numeric", "nominal_values": null, "number_missing_values": 224709}, {"index": 39, "name": "value_euro_fin_1", "data_type": "numeric", "nominal_values": null, "number_missing_values": 119041}, {"index": 40, "name": "value_euro_fin_2", "data_type": "numeric", "nominal_values": null, "number_missing_values": 119254}, {"index": 41, "name": "b_eu_funds", "data_type": "string", "nominal_values": null, "number_missing_values": 130635}, {"index": 42, "name": "top_type", "data_type": "string", "nominal_values": null, "number_missing_values": 2128}, {"index": 43, "name": "b_accelerated", "data_type": "string", "nominal_values": null, "number_missing_values": 561275}, {"index": 44, "name": "out_of_directives", "data_type": "numeric", "nominal_values": null, "number_missing_values": 0}, {"index": 45, "name": "crit_code", "data_type": "string", "nominal_values": null, "number_missing_values": 62431}, {"index": 46, "name": "crit_price_weight", "data_type": "numeric", "nominal_values": null, "number_missing_values": 370512}, {"index": 47, "name": "crit_criteria", "data_type": "string", "nominal_values": null, "number_missing_values": 283086}, {"index": 48, "name": "crit_weights", "data_type": "string", "nominal_values": null, "number_missing_values": 295858}, {"index": 49, "name": "b_electronic_auction", "data_type": "string", "nominal_values": null, "number_missing_values": 132405}, {"index": 50, "name": "number_awards", "data_type": "numeric", "nominal_values": null, "number_missing_values": 0}, {"index": 51, "name": "id_award", "data_type": "numeric", "nominal_values": null, "number_missing_values": 877}, {"index": 52, "name": "id_lot_awarded", "data_type": "numeric", "nominal_values": null, "number_missing_values": 210812}, {"index": 53, "name": "info_on_non_award", "data_type": "string", "nominal_values": null, "number_missing_values": 565149}, {"index": 54, "name": "info_unpublished", "data_type": "string", "nominal_values": null, "number_missing_values": 877}, {"index": 55, "name": "b_awarded_to_a_group", "data_type": "string", "nominal_values": null, "number_missing_values": 564985}, {"index": 56, "name": "win_name", "data_type": "string", "nominal_values": null, "number_missing_values": 7079}, {"index": 57, "name": "win_nationalid", "data_type": "string", "nominal_values": null, "number_missing_values": 565119}, {"index": 58, "name": "win_address", "data_type": "string", "nominal_values": null, "number_missing_values": 94162}, {"index": 59, "name": "win_town", "data_type": "string", "nominal_values": null, "number_missing_values": 76570}, {"index": 60, "name": "win_postal_code", "data_type": "string", "nominal_values": null, "number_missing_values": 88480}, {"index": 61, "name": "win_country_code", "data_type": "string", "nominal_values": null, "number_missing_values": 108842}, {"index": 62, "name": "b_contractor_sme", "data_type": "string", "nominal_values": null, "number_missing_values": 564985}, {"index": 63, "name": "contract_number", "data_type": "string", "nominal_values": null, "number_missing_values": 170453}, {"index": 64, "name": "title", "data_type": "string", "nominal_values": null, "number_missing_values": 220441}, {"index": 65, "name": "number_offers", "data_type": "numeric", "nominal_values": null, "number_missing_values": 104512}, {"index": 66, "name": "number_tenders_sme", "data_type": "numeric", "nominal_values": null, "number_missing_values": 565113}, {"index": 67, "name": "number_tenders_other_eu", "data_type": "numeric", "nominal_values": null, "number_missing_values": 565118}, {"index": 68, "name": "number_tenders_non_eu", "data_type": "numeric", "nominal_values": null, "number_missing_values": 565119}, {"index": 69, "name": "number_offers_electr", "data_type": "numeric", "nominal_values": null, "number_missing_values": 510304}, {"index": 70, "name": "award_est_value_euro", "data_type": "numeric", "nominal_values": null, "number_missing_values": 332063}, {"index": 71, "name": "award_value_euro", "data_type": "numeric", "nominal_values": null, "number_missing_values": 199954}, {"index": 72, "name": "award_value_euro_fin_1", "data_type": "numeric", "nominal_values": null, "number_missing_values": 160746}, {"index": 73, "name": "b_subcontracted", "data_type": "string", "nominal_values": null, "number_missing_values": 205034}, {"index": 74, "name": "dt_award", "data_type": "string", "nominal_values": null, "number_missing_values": 38878}], "qualities": null}