{"dataset_id": 42973, "name": "ct-slice-localization", "version": 1, "description": "**Author**: F. Graf, H.-P. Kriegel, M. Schubert, S. Poelsterl, A. Cavallaro \n**Source**: [UCI](https://archive.ics.uci.edu/ml/datasets/Relative+location+of+CT+slices+on+axial+axis) - 2011\n**Please cite**: [UCI](https://archive.ics.uci.edu/ml/citation_policy.html)  \n\n**Relative location of CT slices on axial axis Data Set**\n\nThe dataset consists of 384 features extracted from CT images. The class variable is numeric and denotes the relative location of the CT slice on the axial axis of the human body. The data was retrieved from a set of 53500 CT images from 74 different patients (43 male, 31 female).  Each CT slice is described by two histograms in polar space. The first histogram describes the location of bone structures in the image, the second the location of air inclusions inside of the body.  Both histograms are concatenated to form the final feature vector.  Bins that are outside of the image are marked with the value -0.25.  The class variable (relative location of an image on the axial axis) was constructed by manually annotating up to 10 different distinct landmarks in each CT Volume with known location. The location of slices in between \nlandmarks was interpolated.\n\n### Attribute information\n\n1. patientId: Each ID identifies a different patient \n2. - 241.: Histogram describing bone structures \n242. - 385.: Histogram describing air inclusions \n386. reference: Relative location of the image on the axial axis (class \nvalue). Values are in the range [0; 180] where 0 denotes \nthe top of the head and 180 the soles of the feet.", "creator": ["F. Graf", "H.-P. Kriegel", "M. Schubert", "S. Poelsterl", "A. Cavallaro"], "contributor": null, "collection_date": "07-07-2011", "upload_date": "2021-05-28T11:02:03", "language": "English", "license": "Publicly available", "default_target_attribute": null, "row_id_attribute": null, "ignore_attribute": null, "tags": null, "features": [{"index": 0, "name": "patientId", "data_type": "numeric", "nominal_values": null, "number_missing_values": 0}, {"index": 1, "name": "value0", "data_type": "numeric", "nominal_values": null, "number_missing_values": 0}, {"index": 2, "name": "value1", "data_type": "numeric", "nominal_values": null, "number_missing_values": 0}, {"index": 3, "name": "value2", "data_type": "numeric", "nominal_values": null, "number_missing_values": 0}, {"index": 4, "name": "value3", "data_type": "numeric", "nominal_values": null, "number_missing_values": 0}, {"index": 5, "name": "value4", "data_type": "numeric", "nominal_values": null, "number_missing_values": 0}, {"index": 6, "name": "value5", "data_type": "numeric", "nominal_values": null, "number_missing_values": 0}, {"index": 7, "name": "value6", "data_type": "numeric", "nominal_values": null, "number_missing_values": 0}, {"index": 8, "name": "value7", "data_type": "numeric", "nominal_values": null, "number_missing_values": 0}, {"index": 9, "name": "value8", "data_type": "numeric", "nominal_values": null, "number_missing_values": 0}, {"index": 10, "name": "value9", "data_type": "numeric", "nominal_values": null, "number_missing_values": 0}, {"index": 11, "name": "value10", "data_type": "numeric", "nominal_values": null, "number_missing_values": 0}, {"index": 12, "name": "value11", "data_type": "numeric", "nominal_values": null, "number_missing_values": 0}, {"index": 13, "name": "value12", "data_type": "numeric", "nominal_values": null, "number_missing_values": 0}, {"index": 14, "name": "value13", "data_type": "numeric", "nominal_values": null, "number_missing_values": 0}, {"index": 15, "name": "value14", "data_type": "numeric", "nominal_values": null, "number_missing_values": 0}, {"index": 16, "name": "value15", "data_type": "numeric", "nominal_values": null, "number_missing_values": 0}, {"index": 17, "name": "value16", "data_type": "numeric", "nominal_values": null, "number_missing_values": 0}, {"index": 18, "name": "value17", "data_type": "numeric", "nominal_values": null, "number_missing_values": 0}, {"index": 19, "name": "value18", "data_type": "numeric", "nominal_values": null, "number_missing_values": 0}, {"index": 20, "name": "value19", "data_type": "numeric", "nominal_values": null, "number_missing_values": 0}, {"index": 21, "name": "value20", "data_type": "numeric", "nominal_values": null, "number_missing_values": 0}, {"index": 22, "name": "value21", "data_type": "numeric", "nominal_values": null, "number_missing_values": 0}, {"index": 23, "name": "value22", "data_type": "numeric", "nominal_values": null, "number_missing_values": 0}, {"index": 24, "name": "value23", "data_type": "numeric", "nominal_values": null, "number_missing_values": 0}, {"index": 25, "name": "value24", "data_type": "numeric", "nominal_values": null, "number_missing_values": 0}, {"index": 26, "name": "value25", "data_type": "numeric", "nominal_values": null, "number_missing_values": 0}, {"index": 27, "name": "value26", "data_type": "numeric", "nominal_values": null, "number_missing_values": 0}, {"index": 28, "name": "value27", "data_type": "numeric", "nominal_values": null, "number_missing_values": 0}, {"index": 29, "name": "value28", "data_type": "numeric", "nominal_values": null, "number_missing_values": 0}, {"index": 30, "name": "value29", "data_type": "numeric", "nominal_values": null, "number_missing_values": 0}, {"index": 31, "name": "value30", "data_type": "numeric", "nominal_values": null, "number_missing_values": 0}, {"index": 32, "name": "value31", "data_type": "numeric", "nominal_values": null, "number_missing_values": 0}, {"index": 33, "name": "value32", "data_type": "numeric", "nominal_values": null, "number_missing_values": 0}, {"index": 34, "name": "value33", "data_type": "numeric", "nominal_values": null, "number_missing_values": 0}, {"index": 35, "name": "value34", "data_type": "numeric", "nominal_values": null, "number_missing_values": 0}, {"index": 36, "name": "value35", "data_type": "numeric", "nominal_values": null, "number_missing_values": 0}, {"index": 37, "name": "value36", "data_type": "numeric", "nominal_values": null, "number_missing_values": 0}, {"index": 38, "name": "value37", "data_type": "numeric", "nominal_values": null, "number_missing_values": 0}, {"index": 39, "name": "value38", "data_type": "numeric", "nominal_values": null, "number_missing_values": 0}, {"index": 40, "name": "value39", "data_type": "numeric", "nominal_values": null, "number_missing_values": 0}, {"index": 41, "name": "value40", "data_type": "numeric", "nominal_values": null, "number_missing_values": 0}, {"index": 42, "name": "value41", "data_type": "numeric", "nominal_values": null, "number_missing_values": 0}, {"index": 43, "name": "value42", "data_type": "numeric", "nominal_values": null, "number_missing_values": 0}, {"index": 44, "name": "value43", "data_type": "numeric", "nominal_values": null, "number_missing_values": 0}, {"index": 45, "name": "value44", "data_type": "numeric", "nominal_values": null, "number_missing_values": 0}, {"index": 46, "name": "value45", "data_type": "numeric", "nominal_values": null, "number_missing_values": 0}, {"index": 47, "name": "value46", "data_type": "numeric", "nominal_values": null, "number_missing_values": 0}, {"index": 48, "name": "value47", "data_type": "numeric", "nominal_values": null, "number_missing_values": 0}, {"index": 49, "name": "value48", "data_type": "numeric", "nominal_values": null, "number_missing_values": 0}, {"index": 50, "name": "value49", "data_type": "numeric", "nominal_values": null, "number_missing_values": 0}, {"index": 51, "name": "value50", "data_type": "numeric", "nominal_values": null, "number_missing_values": 0}, {"index": 52, "name": "value51", "data_type": "numeric", "nominal_values": null, "number_missing_values": 0}, {"index": 53, "name": "value52", "data_type": "numeric", "nominal_values": null, "number_missing_values": 0}, {"index": 54, "name": "value53", "data_type": "numeric", "nominal_values": null, "number_missing_values": 0}, {"index": 55, "name": "value54", "data_type": "numeric", "nominal_values": null, "number_missing_values": 0}, {"index": 56, "name": "value55", "data_type": "numeric", "nominal_values": null, "number_missing_values": 0}, {"index": 57, "name": "value56", "data_type": "numeric", "nominal_values": null, "number_missing_values": 0}, {"index": 58, "name": "value57", "data_type": "numeric", "nominal_values": null, "number_missing_values": 0}, {"index": 59, "name": "value58", "data_type": "numeric", "nominal_values": null, "number_missing_values": 0}, {"index": 60, "name": "value59", "data_type": "numeric", "nominal_values": null, "number_missing_values": 0}, {"index": 61, "name": "value60", "data_type": "numeric", "nominal_values": null, "number_missing_values": 0}, {"index": 62, "name": "value61", "data_type": "numeric", "nominal_values": null, "number_missing_values": 0}, {"index": 63, "name": "value62", "data_type": "numeric", "nominal_values": null, "number_missing_values": 0}, {"index": 64, "name": "value63", "data_type": "numeric", "nominal_values": null, "number_missing_values": 0}, {"index": 65, "name": "value64", "data_type": "numeric", "nominal_values": null, "number_missing_values": 0}, {"index": 66, "name": "value65", "data_type": "numeric", "nominal_values": null, "number_missing_values": 0}, {"index": 67, "name": "value66", "data_type": "numeric", "nominal_values": null, "number_missing_values": 0}, {"index": 68, "name": "value67", "data_type": "numeric", "nominal_values": null, "number_missing_values": 0}, {"index": 69, "name": "value68", "data_type": "numeric", "nominal_values": null, "number_missing_values": 0}, {"index": 70, "name": "value69", "data_type": "numeric", "nominal_values": null, "number_missing_values": 0}, {"index": 71, "name": "value70", "data_type": "numeric", "nominal_values": null, "number_missing_values": 0}, {"index": 72, "name": "value71", "data_type": "numeric", "nominal_values": null, "number_missing_values": 0}, {"index": 73, "name": "value72", "data_type": "numeric", "nominal_values": null, "number_missing_values": 0}, {"index": 74, "name": "value73", "data_type": "numeric", "nominal_values": null, "number_missing_values": 0}, {"index": 75, "name": "value74", "data_type": "numeric", "nominal_values": null, "number_missing_values": 0}, {"index": 76, "name": "value75", "data_type": "numeric", "nominal_values": null, "number_missing_values": 0}, {"index": 77, "name": "value76", "data_type": "numeric", "nominal_values": null, "number_missing_values": 0}, {"index": 78, "name": "value77", "data_type": "numeric", "nominal_values": null, "number_missing_values": 0}, {"index": 79, "name": "value78", "data_type": "numeric", "nominal_values": null, "number_missing_values": 0}, {"index": 80, "name": "value79", "data_type": "numeric", "nominal_values": null, "number_missing_values": 0}, {"index": 81, "name": "value80", "data_type": "numeric", "nominal_values": null, "number_missing_values": 0}, {"index": 82, "name": "value81", "data_type": "numeric", "nominal_values": null, "number_missing_values": 0}, {"index": 83, "name": "value82", "data_type": "numeric", "nominal_values": null, "number_missing_values": 0}, {"index": 84, "name": "value83", "data_type": "numeric", "nominal_values": null, "number_missing_values": 0}, {"index": 85, "name": "value84", "data_type": "numeric", "nominal_values": null, "number_missing_values": 0}, {"index": 86, "name": "value85", "data_type": "numeric", "nominal_values": null, "number_missing_values": 0}, {"index": 87, "name": "value86", "data_type": "numeric", "nominal_values": null, "number_missing_values": 0}, {"index": 88, "name": "value87", "data_type": "numeric", "nominal_values": null, "number_missing_values": 0}, {"index": 89, "name": "value88", "data_type": "numeric", "nominal_values": null, "number_missing_values": 0}, {"index": 90, "name": "value89", "data_type": "numeric", "nominal_values": null, "number_missing_values": 0}, {"index": 91, "name": "value90", "data_type": "numeric", "nominal_values": null, "number_missing_values": 0}, {"index": 92, "name": "value91", "data_type": "numeric", "nominal_values": null, "number_missing_values": 0}, {"index": 93, "name": "value92", "data_type": "numeric", "nominal_values": null, "number_missing_values": 0}, {"index": 94, "name": "value93", "data_type": "numeric", "nominal_values": null, "number_missing_values": 0}, {"index": 95, "name": "value94", "data_type": "numeric", "nominal_values": null, "number_missing_values": 0}, {"index": 96, "name": "value95", "data_type": "numeric", "nominal_values": null, "number_missing_values": 0}, {"index": 97, "name": "value96", "data_type": "numeric", "nominal_values": null, "number_missing_values": 0}, {"index": 98, "name": "value97", "data_type": "numeric", "nominal_values": null, "number_missing_values": 0}, {"index": 99, "name": "value98", "data_type": "numeric", "nominal_values": null, "number_missing_values": 0}, {"index": 100, "name": "value99", "data_type": "numeric", "nominal_values": null, "number_missing_values": 0}, {"index": 101, "name": "value100", "data_type": "numeric", "nominal_values": null, "number_missing_values": 0}, {"index": 102, "name": "value101", "data_type": "numeric", "nominal_values": null, "number_missing_values": 0}, {"index": 103, "name": "value102", "data_type": "numeric", "nominal_values": null, "number_missing_values": 0}, {"index": 104, "name": "value103", "data_type": "numeric", "nominal_values": null, "number_missing_values": 0}, {"index": 105, "name": "value104", "data_type": "numeric", "nominal_values": null, "number_missing_values": 0}, {"index": 106, "name": "value105", "data_type": "numeric", "nominal_values": null, "number_missing_values": 0}, {"index": 107, "name": "value106", "data_type": "numeric", "nominal_values": null, "number_missing_values": 0}, {"index": 108, "name": "value107", "data_type": "numeric", "nominal_values": null, "number_missing_values": 0}, {"index": 109, "name": "value108", "data_type": "numeric", "nominal_values": null, "number_missing_values": 0}, {"index": 110, "name": "value109", "data_type": "numeric", "nominal_values": null, "number_missing_values": 0}, {"index": 111, "name": "value110", "data_type": "numeric", "nominal_values": null, "number_missing_values": 0}, {"index": 112, "name": "value111", "data_type": "numeric", "nominal_values": null, "number_missing_values": 0}, {"index": 113, "name": "value112", "data_type": "numeric", "nominal_values": null, "number_missing_values": 0}, {"index": 114, "name": "value113", "data_type": "numeric", "nominal_values": null, "number_missing_values": 0}, {"index": 115, "name": "value114", "data_type": "numeric", "nominal_values": null, "number_missing_values": 0}, {"index": 116, "name": "value115", "data_type": "numeric", "nominal_values": null, "number_missing_values": 0}, {"index": 117, "name": "value116", "data_type": "numeric", "nominal_values": null, "number_missing_values": 0}, {"index": 118, "name": "value117", "data_type": "numeric", "nominal_values": null, "number_missing_values": 0}, {"index": 119, "name": "value118", "data_type": "numeric", "nominal_values": null, "number_missing_values": 0}, {"index": 120, "name": "value119", "data_type": "numeric", "nominal_values": null, "number_missing_values": 0}, {"index": 121, "name": "value120", "data_type": "numeric", "nominal_values": null, "number_missing_values": 0}, {"index": 122, "name": "value121", "data_type": "numeric", "nominal_values": null, "number_missing_values": 0}, {"index": 123, "name": "value122", "data_type": "numeric", "nominal_values": null, "number_missing_values": 0}, {"index": 124, "name": "value123", "data_type": "numeric", "nominal_values": null, "number_missing_values": 0}, {"index": 125, "name": "value124", "data_type": "numeric", "nominal_values": null, "number_missing_values": 0}, {"index": 126, "name": "value125", "data_type": "numeric", "nominal_values": null, "number_missing_values": 0}, {"index": 127, "name": "value126", "data_type": "numeric", "nominal_values": null, "number_missing_values": 0}, {"index": 128, "name": "value127", "data_type": "numeric", "nominal_values": null, "number_missing_values": 0}, {"index": 129, "name": "value128", "data_type": "numeric", "nominal_values": null, "number_missing_values": 0}, {"index": 130, "name": "value129", "data_type": "numeric", "nominal_values": null, "number_missing_values": 0}, {"index": 131, "name": "value130", "data_type": "numeric", "nominal_values": null, "number_missing_values": 0}, {"index": 132, "name": "value131", "data_type": "numeric", "nominal_values": null, "number_missing_values": 0}, {"index": 133, "name": "value132", "data_type": "numeric", "nominal_values": null, "number_missing_values": 0}, {"index": 134, "name": "value133", "data_type": "numeric", "nominal_values": null, "number_missing_values": 0}, {"index": 135, "name": "value134", "data_type": "numeric", "nominal_values": null, "number_missing_values": 0}, {"index": 136, "name": "value135", "data_type": "numeric", "nominal_values": null, "number_missing_values": 0}, {"index": 137, "name": "value136", "data_type": "numeric", "nominal_values": null, "number_missing_values": 0}, {"index": 138, "name": "value137", "data_type": "numeric", "nominal_values": null, "number_missing_values": 0}, {"index": 139, "name": "value138", "data_type": "numeric", "nominal_values": null, "number_missing_values": 0}, {"index": 140, "name": "value139", "data_type": "numeric", "nominal_values": null, "number_missing_values": 0}, {"index": 141, "name": "value140", "data_type": "numeric", "nominal_values": null, "number_missing_values": 0}, {"index": 142, "name": "value141", "data_type": "numeric", "nominal_values": null, "number_missing_values": 0}, {"index": 143, "name": "value142", "data_type": "numeric", "nominal_values": null, "number_missing_values": 0}, {"index": 144, "name": "value143", "data_type": "numeric", "nominal_values": null, "number_missing_values": 0}, {"index": 145, "name": "value144", "data_type": "numeric", "nominal_values": null, "number_missing_values": 0}, {"index": 146, "name": "value145", "data_type": "numeric", "nominal_values": null, "number_missing_values": 0}, {"index": 147, "name": "value146", "data_type": "numeric", "nominal_values": null, "number_missing_values": 0}, {"index": 148, "name": "value147", "data_type": "numeric", "nominal_values": null, "number_missing_values": 0}, {"index": 149, "name": "value148", "data_type": "numeric", "nominal_values": null, "number_missing_values": 0}, {"index": 150, "name": "value149", "data_type": "numeric", "nominal_values": null, "number_missing_values": 0}, {"index": 151, "name": "value150", "data_type": "numeric", "nominal_values": null, "number_missing_values": 0}, {"index": 152, "name": "value151", "data_type": "numeric", "nominal_values": null, "number_missing_values": 0}, {"index": 153, "name": "value152", "data_type": "numeric", "nominal_values": null, "number_missing_values": 0}, {"index": 154, "name": "value153", "data_type": "numeric", "nominal_values": null, "number_missing_values": 0}, {"index": 155, "name": "value154", "data_type": "numeric", "nominal_values": null, "number_missing_values": 0}, {"index": 156, "name": "value155", "data_type": "numeric", "nominal_values": null, "number_missing_values": 0}, {"index": 157, "name": "value156", "data_type": "numeric", "nominal_values": null, "number_missing_values": 0}, {"index": 158, "name": "value157", "data_type": "numeric", "nominal_values": null, "number_missing_values": 0}, {"index": 159, "name": "value158", "data_type": "numeric", "nominal_values": null, "number_missing_values": 0}, {"index": 160, "name": "value159", "data_type": "numeric", "nominal_values": null, "number_missing_values": 0}, {"index": 161, "name": "value160", "data_type": "numeric", "nominal_values": null, "number_missing_values": 0}, {"index": 162, "name": "value161", "data_type": "numeric", "nominal_values": null, "number_missing_values": 0}, {"index": 163, "name": "value162", "data_type": "numeric", "nominal_values": null, "number_missing_values": 0}, {"index": 164, "name": "value163", "data_type": "numeric", "nominal_values": null, "number_missing_values": 0}, {"index": 165, "name": "value164", "data_type": "numeric", "nominal_values": null, "number_missing_values": 0}, {"index": 166, "name": "value165", "data_type": "numeric", "nominal_values": null, "number_missing_values": 0}, {"index": 167, "name": "value166", "data_type": "numeric", "nominal_values": null, "number_missing_values": 0}, {"index": 168, "name": "value167", "data_type": "numeric", "nominal_values": null, "number_missing_values": 0}, {"index": 169, "name": "value168", "data_type": "numeric", "nominal_values": null, "number_missing_values": 0}, {"index": 170, "name": "value169", "data_type": "numeric", "nominal_values": null, "number_missing_values": 0}, {"index": 171, "name": "value170", "data_type": "numeric", "nominal_values": null, "number_missing_values": 0}, {"index": 172, "name": "value171", "data_type": "numeric", "nominal_values": null, "number_missing_values": 0}, {"index": 173, "name": "value172", "data_type": "numeric", "nominal_values": null, "number_missing_values": 0}, {"index": 174, "name": "value173", "data_type": "numeric", "nominal_values": null, "number_missing_values": 0}, {"index": 175, "name": "value174", "data_type": "numeric", "nominal_values": null, "number_missing_values": 0}, {"index": 176, "name": "value175", "data_type": "numeric", "nominal_values": null, "number_missing_values": 0}, {"index": 177, "name": "value176", "data_type": "numeric", "nominal_values": null, "number_missing_values": 0}, {"index": 178, "name": "value177", "data_type": "numeric", "nominal_values": null, "number_missing_values": 0}, {"index": 179, "name": "value178", "data_type": "numeric", "nominal_values": null, "number_missing_values": 0}, {"index": 180, "name": "value179", "data_type": "numeric", "nominal_values": null, "number_missing_values": 0}, {"index": 181, "name": "value180", "data_type": "numeric", "nominal_values": null, "number_missing_values": 0}, {"index": 182, "name": "value181", "data_type": "numeric", "nominal_values": null, "number_missing_values": 0}, {"index": 183, "name": "value182", "data_type": "numeric", "nominal_values": null, "number_missing_values": 0}, {"index": 184, "name": "value183", "data_type": "numeric", "nominal_values": null, "number_missing_values": 0}, {"index": 185, "name": "value184", "data_type": "numeric", "nominal_values": null, "number_missing_values": 0}, {"index": 186, "name": "value185", "data_type": "numeric", "nominal_values": null, "number_missing_values": 0}, {"index": 187, "name": "value186", "data_type": "numeric", "nominal_values": null, "number_missing_values": 0}, {"index": 188, "name": "value187", "data_type": "numeric", "nominal_values": null, "number_missing_values": 0}, {"index": 189, "name": "value188", "data_type": "numeric", "nominal_values": null, "number_missing_values": 0}, {"index": 190, "name": "value189", "data_type": "numeric", "nominal_values": null, "number_missing_values": 0}, {"index": 191, "name": "value190", "data_type": "numeric", "nominal_values": null, "number_missing_values": 0}, {"index": 192, "name": "value191", "data_type": "numeric", "nominal_values": null, "number_missing_values": 0}, {"index": 193, "name": "value192", "data_type": "numeric", "nominal_values": null, "number_missing_values": 0}, {"index": 194, "name": "value193", "data_type": "numeric", "nominal_values": null, "number_missing_values": 0}, {"index": 195, "name": "value194", "data_type": "numeric", "nominal_values": null, "number_missing_values": 0}, {"index": 196, "name": "value195", "data_type": "numeric", "nominal_values": null, "number_missing_values": 0}, {"index": 197, "name": "value196", "data_type": "numeric", "nominal_values": null, "number_missing_values": 0}, {"index": 198, "name": "value197", "data_type": "numeric", "nominal_values": null, "number_missing_values": 0}, {"index": 199, "name": "value198", "data_type": "numeric", "nominal_values": null, "number_missing_values": 0}, {"index": 200, "name": "value199", "data_type": "numeric", "nominal_values": null, "number_missing_values": 0}, {"index": 201, "name": "value200", "data_type": "numeric", "nominal_values": null, "number_missing_values": 0}, {"index": 202, "name": "value201", "data_type": "numeric", "nominal_values": null, "number_missing_values": 0}, {"index": 203, "name": "value202", "data_type": "numeric", "nominal_values": null, "number_missing_values": 0}, {"index": 204, "name": "value203", "data_type": "numeric", "nominal_values": null, "number_missing_values": 0}, {"index": 205, "name": "value204", "data_type": "numeric", "nominal_values": null, "number_missing_values": 0}, {"index": 206, "name": "value205", "data_type": "numeric", "nominal_values": null, "number_missing_values": 0}, {"index": 207, "name": "value206", "data_type": "numeric", "nominal_values": null, "number_missing_values": 0}, {"index": 208, "name": "value207", "data_type": "numeric", "nominal_values": null, "number_missing_values": 0}, {"index": 209, "name": "value208", "data_type": "numeric", "nominal_values": null, "number_missing_values": 0}, {"index": 210, "name": "value209", "data_type": "numeric", "nominal_values": null, "number_missing_values": 0}, {"index": 211, "name": "value210", "data_type": "numeric", "nominal_values": null, "number_missing_values": 0}, {"index": 212, "name": "value211", "data_type": "numeric", "nominal_values": null, "number_missing_values": 0}, {"index": 213, "name": "value212", "data_type": "numeric", "nominal_values": null, "number_missing_values": 0}, {"index": 214, "name": "value213", "data_type": "numeric", "nominal_values": null, "number_missing_values": 0}, {"index": 215, "name": "value214", "data_type": "numeric", "nominal_values": null, "number_missing_values": 0}, {"index": 216, "name": "value215", "data_type": "numeric", "nominal_values": null, "number_missing_values": 0}, {"index": 217, "name": "value216", "data_type": "numeric", "nominal_values": null, "number_missing_values": 0}, {"index": 218, "name": "value217", "data_type": "numeric", "nominal_values": null, "number_missing_values": 0}, {"index": 219, "name": "value218", "data_type": "numeric", "nominal_values": null, "number_missing_values": 0}, {"index": 220, "name": "value219", "data_type": "numeric", "nominal_values": null, "number_missing_values": 0}, {"index": 221, "name": "value220", "data_type": "numeric", "nominal_values": null, "number_missing_values": 0}, {"index": 222, "name": "value221", "data_type": "numeric", "nominal_values": null, "number_missing_values": 0}, {"index": 223, "name": "value222", "data_type": "numeric", "nominal_values": null, "number_missing_values": 0}, {"index": 224, "name": "value223", "data_type": "numeric", "nominal_values": null, "number_missing_values": 0}, {"index": 225, "name": "value224", "data_type": "numeric", "nominal_values": null, "number_missing_values": 0}, {"index": 226, "name": "value225", "data_type": "numeric", "nominal_values": null, "number_missing_values": 0}, {"index": 227, "name": "value226", "data_type": "numeric", "nominal_values": null, "number_missing_values": 0}, {"index": 228, "name": "value227", "data_type": "numeric", "nominal_values": null, "number_missing_values": 0}, {"index": 229, "name": "value228", "data_type": "numeric", "nominal_values": null, "number_missing_values": 0}, {"index": 230, "name": "value229", "data_type": "numeric", "nominal_values": null, "number_missing_values": 0}, {"index": 231, "name": "value230", "data_type": "numeric", "nominal_values": null, "number_missing_values": 0}, {"index": 232, "name": "value231", "data_type": "numeric", "nominal_values": null, "number_missing_values": 0}, {"index": 233, "name": "value232", "data_type": "numeric", "nominal_values": null, "number_missing_values": 0}, {"index": 234, "name": "value233", "data_type": "numeric", "nominal_values": null, "number_missing_values": 0}, {"index": 235, "name": "value234", "data_type": "numeric", "nominal_values": null, "number_missing_values": 0}, {"index": 236, "name": "value235", "data_type": "numeric", "nominal_values": null, "number_missing_values": 0}, {"index": 237, "name": "value236", "data_type": "numeric", "nominal_values": null, "number_missing_values": 0}, {"index": 238, "name": "value237", "data_type": "numeric", "nominal_values": null, "number_missing_values": 0}, {"index": 239, "name": "value238", "data_type": "numeric", "nominal_values": null, "number_missing_values": 0}, {"index": 240, "name": "value239", "data_type": "numeric", "nominal_values": null, "number_missing_values": 0}, {"index": 241, "name": "value240", "data_type": "numeric", "nominal_values": null, "number_missing_values": 0}, {"index": 242, "name": "value241", "data_type": "numeric", "nominal_values": null, "number_missing_values": 0}, {"index": 243, "name": "value242", "data_type": "numeric", "nominal_values": null, "number_missing_values": 0}, {"index": 244, "name": "value243", "data_type": "numeric", "nominal_values": null, "number_missing_values": 0}, {"index": 245, "name": "value244", "data_type": "numeric", "nominal_values": null, "number_missing_values": 0}, {"index": 246, "name": "value245", "data_type": "numeric", "nominal_values": null, "number_missing_values": 0}, {"index": 247, "name": "value246", "data_type": "numeric", "nominal_values": null, "number_missing_values": 0}, {"index": 248, "name": "value247", "data_type": "numeric", "nominal_values": null, "number_missing_values": 0}, {"index": 249, "name": "value248", "data_type": "numeric", "nominal_values": null, "number_missing_values": 0}, {"index": 250, "name": "value249", "data_type": "numeric", "nominal_values": null, "number_missing_values": 0}, {"index": 251, "name": "value250", "data_type": "numeric", "nominal_values": null, "number_missing_values": 0}, {"index": 252, "name": "value251", "data_type": "numeric", "nominal_values": null, "number_missing_values": 0}, {"index": 253, "name": "value252", "data_type": "numeric", "nominal_values": null, "number_missing_values": 0}, {"index": 254, "name": "value253", "data_type": "numeric", "nominal_values": null, "number_missing_values": 0}, {"index": 255, "name": "value254", "data_type": "numeric", "nominal_values": null, "number_missing_values": 0}, {"index": 256, "name": "value255", "data_type": "numeric", "nominal_values": null, "number_missing_values": 0}, {"index": 257, "name": "value256", "data_type": "numeric", "nominal_values": null, "number_missing_values": 0}, {"index": 258, "name": "value257", "data_type": "numeric", "nominal_values": null, "number_missing_values": 0}, {"index": 259, "name": "value258", "data_type": "numeric", "nominal_values": null, "number_missing_values": 0}, {"index": 260, "name": "value259", "data_type": "numeric", "nominal_values": null, "number_missing_values": 0}, {"index": 261, "name": "value260", "data_type": "numeric", "nominal_values": null, "number_missing_values": 0}, {"index": 262, "name": "value261", "data_type": "numeric", "nominal_values": null, "number_missing_values": 0}, {"index": 263, "name": "value262", "data_type": "numeric", "nominal_values": null, "number_missing_values": 0}, {"index": 264, "name": "value263", "data_type": "numeric", "nominal_values": null, "number_missing_values": 0}, {"index": 265, "name": "value264", "data_type": "numeric", "nominal_values": null, "number_missing_values": 0}, {"index": 266, "name": "value265", "data_type": "numeric", "nominal_values": null, "number_missing_values": 0}, {"index": 267, "name": "value266", "data_type": "numeric", "nominal_values": null, "number_missing_values": 0}, {"index": 268, "name": "value267", "data_type": "numeric", "nominal_values": null, "number_missing_values": 0}, {"index": 269, "name": "value268", "data_type": "numeric", "nominal_values": null, "number_missing_values": 0}, {"index": 270, "name": "value269", "data_type": "numeric", "nominal_values": null, "number_missing_values": 0}, {"index": 271, "name": "value270", "data_type": "numeric", "nominal_values": null, "number_missing_values": 0}, {"index": 272, "name": "value271", "data_type": "numeric", "nominal_values": null, "number_missing_values": 0}, {"index": 273, "name": "value272", "data_type": "numeric", "nominal_values": null, "number_missing_values": 0}, {"index": 274, "name": "value273", "data_type": "numeric", "nominal_values": null, "number_missing_values": 0}, {"index": 275, "name": "value274", "data_type": "numeric", "nominal_values": null, "number_missing_values": 0}, {"index": 276, "name": "value275", "data_type": "numeric", "nominal_values": null, "number_missing_values": 0}, {"index": 277, "name": "value276", "data_type": "numeric", "nominal_values": null, "number_missing_values": 0}, {"index": 278, "name": "value277", "data_type": "numeric", "nominal_values": null, "number_missing_values": 0}, {"index": 279, "name": "value278", "data_type": "numeric", "nominal_values": null, "number_missing_values": 0}, {"index": 280, "name": "value279", "data_type": "numeric", "nominal_values": null, "number_missing_values": 0}, {"index": 281, "name": "value280", "data_type": "numeric", "nominal_values": null, "number_missing_values": 0}, {"index": 282, "name": "value281", "data_type": "numeric", "nominal_values": null, "number_missing_values": 0}, {"index": 283, "name": "value282", "data_type": "numeric", "nominal_values": null, "number_missing_values": 0}, {"index": 284, "name": "value283", "data_type": "numeric", "nominal_values": null, "number_missing_values": 0}, {"index": 285, "name": "value284", "data_type": "numeric", "nominal_values": null, "number_missing_values": 0}, {"index": 286, "name": "value285", "data_type": "numeric", "nominal_values": null, "number_missing_values": 0}, {"index": 287, "name": "value286", "data_type": "numeric", "nominal_values": null, "number_missing_values": 0}, {"index": 288, "name": "value287", "data_type": "numeric", "nominal_values": null, "number_missing_values": 0}, {"index": 289, "name": "value288", "data_type": "numeric", "nominal_values": null, "number_missing_values": 0}, {"index": 290, "name": "value289", "data_type": "numeric", "nominal_values": null, "number_missing_values": 0}, {"index": 291, "name": "value290", "data_type": "numeric", "nominal_values": null, "number_missing_values": 0}, {"index": 292, "name": "value291", "data_type": "numeric", "nominal_values": null, "number_missing_values": 0}, {"index": 293, "name": "value292", "data_type": "numeric", "nominal_values": null, "number_missing_values": 0}, {"index": 294, "name": "value293", "data_type": "numeric", "nominal_values": null, "number_missing_values": 0}, {"index": 295, "name": "value294", "data_type": "numeric", "nominal_values": null, "number_missing_values": 0}, {"index": 296, "name": "value295", "data_type": "numeric", "nominal_values": null, "number_missing_values": 0}, {"index": 297, "name": "value296", "data_type": "numeric", "nominal_values": null, "number_missing_values": 0}, {"index": 298, "name": "value297", "data_type": "numeric", "nominal_values": null, "number_missing_values": 0}, {"index": 299, "name": "value298", "data_type": "numeric", "nominal_values": null, "number_missing_values": 0}, {"index": 300, "name": "value299", "data_type": "numeric", "nominal_values": null, "number_missing_values": 0}, {"index": 301, "name": "value300", "data_type": "numeric", "nominal_values": null, "number_missing_values": 0}, {"index": 302, "name": "value301", "data_type": "numeric", "nominal_values": null, "number_missing_values": 0}, {"index": 303, "name": "value302", "data_type": "numeric", "nominal_values": null, "number_missing_values": 0}, {"index": 304, "name": "value303", "data_type": "numeric", "nominal_values": null, "number_missing_values": 0}, {"index": 305, "name": "value304", "data_type": "numeric", "nominal_values": null, "number_missing_values": 0}, {"index": 306, "name": "value305", "data_type": "numeric", "nominal_values": null, "number_missing_values": 0}, {"index": 307, "name": "value306", "data_type": "numeric", "nominal_values": null, "number_missing_values": 0}, {"index": 308, "name": "value307", "data_type": "numeric", "nominal_values": null, "number_missing_values": 0}, {"index": 309, "name": "value308", "data_type": "numeric", "nominal_values": null, "number_missing_values": 0}, {"index": 310, "name": "value309", "data_type": "numeric", "nominal_values": null, "number_missing_values": 0}, {"index": 311, "name": "value310", "data_type": "numeric", "nominal_values": null, "number_missing_values": 0}, {"index": 312, "name": "value311", "data_type": "numeric", "nominal_values": null, "number_missing_values": 0}, {"index": 313, "name": "value312", "data_type": "numeric", "nominal_values": null, "number_missing_values": 0}, {"index": 314, "name": "value313", "data_type": "numeric", "nominal_values": null, "number_missing_values": 0}, {"index": 315, "name": "value314", "data_type": "numeric", "nominal_values": null, "number_missing_values": 0}, {"index": 316, "name": "value315", "data_type": "numeric", "nominal_values": null, "number_missing_values": 0}, {"index": 317, "name": "value316", "data_type": "numeric", "nominal_values": null, "number_missing_values": 0}, {"index": 318, "name": "value317", "data_type": "numeric", "nominal_values": null, "number_missing_values": 0}, {"index": 319, "name": "value318", "data_type": "numeric", "nominal_values": null, "number_missing_values": 0}, {"index": 320, "name": "value319", "data_type": "numeric", "nominal_values": null, "number_missing_values": 0}, {"index": 321, "name": "value320", "data_type": "numeric", "nominal_values": null, "number_missing_values": 0}, {"index": 322, "name": "value321", "data_type": "numeric", "nominal_values": null, "number_missing_values": 0}, {"index": 323, "name": "value322", "data_type": "numeric", "nominal_values": null, "number_missing_values": 0}, {"index": 324, "name": "value323", "data_type": "numeric", "nominal_values": null, "number_missing_values": 0}, {"index": 325, "name": "value324", "data_type": "numeric", "nominal_values": null, "number_missing_values": 0}, {"index": 326, "name": "value325", "data_type": "numeric", "nominal_values": null, "number_missing_values": 0}, {"index": 327, "name": "value326", "data_type": "numeric", "nominal_values": null, "number_missing_values": 0}, {"index": 328, "name": "value327", "data_type": "numeric", "nominal_values": null, "number_missing_values": 0}, {"index": 329, "name": "value328", "data_type": "numeric", "nominal_values": null, "number_missing_values": 0}, {"index": 330, "name": "value329", "data_type": "numeric", "nominal_values": null, "number_missing_values": 0}, {"index": 331, "name": "value330", "data_type": "numeric", "nominal_values": null, "number_missing_values": 0}, {"index": 332, "name": "value331", "data_type": "numeric", "nominal_values": null, "number_missing_values": 0}, {"index": 333, "name": "value332", "data_type": "numeric", "nominal_values": null, "number_missing_values": 0}, {"index": 334, "name": "value333", "data_type": "numeric", "nominal_values": null, "number_missing_values": 0}, {"index": 335, "name": "value334", "data_type": "numeric", "nominal_values": null, "number_missing_values": 0}, {"index": 336, "name": "value335", "data_type": "numeric", "nominal_values": null, "number_missing_values": 0}, {"index": 337, "name": "value336", "data_type": "numeric", "nominal_values": null, "number_missing_values": 0}, {"index": 338, "name": "value337", "data_type": "numeric", "nominal_values": null, "number_missing_values": 0}, {"index": 339, "name": "value338", "data_type": "numeric", "nominal_values": null, "number_missing_values": 0}, {"index": 340, "name": "value339", "data_type": "numeric", "nominal_values": null, "number_missing_values": 0}, {"index": 341, "name": "value340", "data_type": "numeric", "nominal_values": null, "number_missing_values": 0}, {"index": 342, "name": "value341", "data_type": "numeric", "nominal_values": null, "number_missing_values": 0}, {"index": 343, "name": "value342", "data_type": "numeric", "nominal_values": null, "number_missing_values": 0}, {"index": 344, "name": "value343", "data_type": "numeric", "nominal_values": null, "number_missing_values": 0}, {"index": 345, "name": "value344", "data_type": "numeric", "nominal_values": null, "number_missing_values": 0}, {"index": 346, "name": "value345", "data_type": "numeric", "nominal_values": null, "number_missing_values": 0}, {"index": 347, "name": "value346", "data_type": "numeric", "nominal_values": null, "number_missing_values": 0}, {"index": 348, "name": "value347", "data_type": "numeric", "nominal_values": null, "number_missing_values": 0}, {"index": 349, "name": "value348", "data_type": "numeric", "nominal_values": null, "number_missing_values": 0}, {"index": 350, "name": "value349", "data_type": "numeric", "nominal_values": null, "number_missing_values": 0}, {"index": 351, "name": "value350", "data_type": "numeric", "nominal_values": null, "number_missing_values": 0}, {"index": 352, "name": "value351", "data_type": "numeric", "nominal_values": null, "number_missing_values": 0}, {"index": 353, "name": "value352", "data_type": "numeric", "nominal_values": null, "number_missing_values": 0}, {"index": 354, "name": "value353", "data_type": "numeric", "nominal_values": null, "number_missing_values": 0}, {"index": 355, "name": "value354", "data_type": "numeric", "nominal_values": null, "number_missing_values": 0}, {"index": 356, "name": "value355", "data_type": "numeric", "nominal_values": null, "number_missing_values": 0}, {"index": 357, "name": "value356", "data_type": "numeric", "nominal_values": null, "number_missing_values": 0}, {"index": 358, "name": "value357", "data_type": "numeric", "nominal_values": null, "number_missing_values": 0}, {"index": 359, "name": "value358", "data_type": "numeric", "nominal_values": null, "number_missing_values": 0}, {"index": 360, "name": "value359", "data_type": "numeric", "nominal_values": null, "number_missing_values": 0}, {"index": 361, "name": "value360", "data_type": "numeric", "nominal_values": null, "number_missing_values": 0}, {"index": 362, "name": "value361", "data_type": "numeric", "nominal_values": null, "number_missing_values": 0}, {"index": 363, "name": "value362", "data_type": "numeric", "nominal_values": null, "number_missing_values": 0}, {"index": 364, "name": "value363", "data_type": "numeric", "nominal_values": null, "number_missing_values": 0}, {"index": 365, "name": "value364", "data_type": "numeric", "nominal_values": null, "number_missing_values": 0}, {"index": 366, "name": "value365", "data_type": "numeric", "nominal_values": null, "number_missing_values": 0}, {"index": 367, "name": "value366", "data_type": "numeric", "nominal_values": null, "number_missing_values": 0}, {"index": 368, "name": "value367", "data_type": "numeric", "nominal_values": null, "number_missing_values": 0}, {"index": 369, "name": "value368", "data_type": "numeric", "nominal_values": null, "number_missing_values": 0}, {"index": 370, "name": "value369", "data_type": "numeric", "nominal_values": null, "number_missing_values": 0}, {"index": 371, "name": "value370", "data_type": "numeric", "nominal_values": null, "number_missing_values": 0}, {"index": 372, "name": "value371", "data_type": "numeric", "nominal_values": null, "number_missing_values": 0}, {"index": 373, "name": "value372", "data_type": "numeric", "nominal_values": null, "number_missing_values": 0}, {"index": 374, "name": "value373", "data_type": "numeric", "nominal_values": null, "number_missing_values": 0}, {"index": 375, "name": "value374", "data_type": "numeric", "nominal_values": null, "number_missing_values": 0}, {"index": 376, "name": "value375", "data_type": "numeric", "nominal_values": null, "number_missing_values": 0}, {"index": 377, "name": "value376", "data_type": "numeric", "nominal_values": null, "number_missing_values": 0}, {"index": 378, "name": "value377", "data_type": "numeric", "nominal_values": null, "number_missing_values": 0}, {"index": 379, "name": "value378", "data_type": "numeric", "nominal_values": null, "number_missing_values": 0}, {"index": 380, "name": "value379", "data_type": "numeric", "nominal_values": null, "number_missing_values": 0}, {"index": 381, "name": "value380", "data_type": "numeric", "nominal_values": null, "number_missing_values": 0}, {"index": 382, "name": "value381", "data_type": "numeric", "nominal_values": null, "number_missing_values": 0}, {"index": 383, "name": "value382", "data_type": "numeric", "nominal_values": null, "number_missing_values": 0}, {"index": 384, "name": "value383", "data_type": "numeric", "nominal_values": null, "number_missing_values": 0}, {"index": 385, "name": "reference", "data_type": "numeric", "nominal_values": null, "number_missing_values": 0}], "qualities": {"AutoCorrelation": NaN, "Dimensionality": 0.007214953271028037, "MajorityClassPercentage": NaN, "MajorityClassSize": NaN, "MinorityClassPercentage": NaN, "MinorityClassSize": NaN, "NumberOfBinaryFeatures": 0.0, "NumberOfClasses": NaN, "NumberOfFeatures": 386.0, "NumberOfInstances": 53500.0, "NumberOfInstancesWithMissingValues": 0.0, "NumberOfMissingValues": 0.0, "NumberOfNumericFeatures": 386.0, "NumberOfSymbolicFeatures": 0.0, "PercentageOfBinaryFeatures": 0.0, "PercentageOfInstancesWithMissingValues": 0.0, "PercentageOfMissingValues": 0.0, "PercentageOfNumericFeatures": 100.0, "PercentageOfSymbolicFeatures": 0.0}}