{"dataset_id": 43651, "name": "Winedata", "version": 1, "description": "Context\nThinking of Natural Language Processing as a beginner!!\nThe dataset has been about the wine comments or reviews that has been given by various wine tasters. The concept was to use text classification to classify the commenters over the reviews. This is mainly used to demonstrate the techniques involved in language processing. The assumption is that every taster has some specific style of describing their object of interest.\nContent\nThe columns contain the reviews, country and provinces of wines, their variety and winery they belong to along with commenters or tasters.\nAcknowledgements\nThe kaggle dataset for wine data with comments, the courses regarding the NLP had been very much helpful for understanding and implementation of the concept.", "creator": null, "contributor": null, "collection_date": "01-12-2020", "upload_date": "2022-03-24T01:00:00", "language": "English", "license": "CC0: Public Domain", "default_target_attribute": null, "row_id_attribute": null, "ignore_attribute": null, "tags": null, "features": [{"index": 0, "name": "Unnamed:_0", "data_type": "numeric", "nominal_values": null, "number_missing_values": 0}, {"index": 1, "name": "country", "data_type": "string", "nominal_values": null, "number_missing_values": 63}, {"index": 2, "name": "description", "data_type": "string", "nominal_values": null, "number_missing_values": 0}, {"index": 3, "name": "designation", "data_type": "string", "nominal_values": null, "number_missing_values": 37467}, {"index": 4, "name": "points", "data_type": "numeric", "nominal_values": null, "number_missing_values": 0}, {"index": 5, "name": "price", "data_type": "numeric", "nominal_values": null, "number_missing_values": 8996}, {"index": 6, "name": "province", "data_type": "string", "nominal_values": null, "number_missing_values": 63}, {"index": 7, "name": "region_1", "data_type": "string", "nominal_values": null, "number_missing_values": 21247}, {"index": 8, "name": "region_2", "data_type": "string", "nominal_values": null, "number_missing_values": 79460}, {"index": 9, "name": "taster_name", "data_type": "string", "nominal_values": null, "number_missing_values": 26244}, {"index": 10, "name": "taster_twitter_handle", "data_type": "string", "nominal_values": null, "number_missing_values": 31213}, {"index": 11, "name": "title", "data_type": "string", "nominal_values": null, "number_missing_values": 0}, {"index": 12, "name": "variety", "data_type": "string", "nominal_values": null, "number_missing_values": 1}, {"index": 13, "name": "winery", "data_type": "string", "nominal_values": null, "number_missing_values": 0}], "qualities": {"AutoCorrelation": NaN, "Dimensionality": 0.0001077163367212686, "MajorityClassPercentage": NaN, "MajorityClassSize": NaN, "MinorityClassPercentage": NaN, "MinorityClassSize": NaN, "NumberOfBinaryFeatures": 0.0, "NumberOfClasses": NaN, "NumberOfFeatures": 14.0, "NumberOfInstances": 129971.0, "NumberOfInstancesWithMissingValues": 107586.0, "NumberOfMissingValues": 204754.0, "NumberOfNumericFeatures": 3.0, "NumberOfSymbolicFeatures": 0.0, "PercentageOfBinaryFeatures": 0.0, "PercentageOfInstancesWithMissingValues": 82.7769271606743, "PercentageOfMissingValues": 11.252730004605423, "PercentageOfNumericFeatures": 21.428571428571427, "PercentageOfSymbolicFeatures": 0.0}}