{"dataset_id": 43789, "name": "Used-cars-in-KSA", "version": 1, "description": "** This project display used cars in many different brands to pay. The number of used cars in the website is 1219 cars, I create data frame for them and each car has 9 features and the prediction of this data is car's price. \nI choice used cars in the project in order to use machine learning to predict car's price. Assign fair price for used car has a big issue depend on their features after usr it. So, I tried to collect as much as I can of features to give a good chance for ML to allocate a best price for car.\nThe kind of modeling that match with my data is supervised model because it includes label 'car_price' and use regression type because the target is number. Additionally, it can be used recommender system in this data .**", "creator": null, "contributor": null, "collection_date": "29-01-2021", "upload_date": "2022-03-24T10:27:46", "language": "English", "license": "CC0: Public Domain", "default_target_attribute": null, "row_id_attribute": null, "ignore_attribute": null, "tags": null, "features": [{"index": 0, "name": "Car_Name", "data_type": "string", "nominal_values": null, "number_missing_values": 1220}, {"index": 1, "name": "Car_Brand", "data_type": "string", "nominal_values": null, "number_missing_values": 1220}, {"index": 2, "name": "Year", "data_type": "numeric", "nominal_values": null, "number_missing_values": 0}, {"index": 3, "name": "Max_Mile_km", "data_type": "numeric", "nominal_values": null, "number_missing_values": 0}, {"index": 4, "name": "Min_Mile_km", "data_type": "numeric", "nominal_values": null, "number_missing_values": 0}, {"index": 5, "name": "Kind", "data_type": "string", "nominal_values": null, "number_missing_values": 1159}, {"index": 6, "name": "City_Of_Owner", "data_type": "string", "nominal_values": null, "number_missing_values": 1220}, {"index": 7, "name": "Condition", "data_type": "string", "nominal_values": null, "number_missing_values": 1220}, {"index": 8, "name": "Kind_Of_Motor", "data_type": "string", "nominal_values": null, "number_missing_values": 1220}, {"index": 9, "name": "Color", "data_type": "string", "nominal_values": null, "number_missing_values": 1220}, {"index": 10, "name": "Price", "data_type": "numeric", "nominal_values": null, "number_missing_values": 0}], "qualities": {"AutoCorrelation": NaN, "Dimensionality": 0.009016393442622951, "MajorityClassPercentage": NaN, "MajorityClassSize": NaN, "MinorityClassPercentage": NaN, "MinorityClassSize": NaN, "NumberOfBinaryFeatures": 0.0, "NumberOfClasses": NaN, "NumberOfFeatures": 11.0, "NumberOfInstances": 1220.0, "NumberOfInstancesWithMissingValues": 1220.0, "NumberOfMissingValues": 8479.0, "NumberOfNumericFeatures": 4.0, "NumberOfSymbolicFeatures": 0.0, "PercentageOfBinaryFeatures": 0.0, "PercentageOfInstancesWithMissingValues": 100.0, "PercentageOfMissingValues": 63.18181818181819, "PercentageOfNumericFeatures": 36.36363636363637, "PercentageOfSymbolicFeatures": 0.0}}