{"dataset_id": 842, "name": "analcatdata_runshoes", "version": 2, "description": "**Author**:   \n**Source**: Unknown - Date unknown  \n**Please cite**:   \n\nBinarized version of the original data set (see version 1). It converts the numeric target feature to a two-class nominal target feature by computing the mean and classifying all instances with a lower target value as positive ('P') and all others as negative ('N').", "creator": null, "contributor": null, "collection_date": null, "upload_date": "2014-10-04T14:35:03", "language": null, "license": "Public", "default_target_attribute": "binaryClass", "row_id_attribute": null, "ignore_attribute": null, "tags": ["mythbusting_1", "study_1", "study_15", "study_20", "study_41"], "features": [{"index": 0, "name": "Male", "data_type": "nominal", "nominal_values": ["0", "1"], "number_missing_values": 0}, {"index": 1, "name": "Married", "data_type": "nominal", "nominal_values": ["0", "1"], "number_missing_values": 0}, {"index": 2, "name": "Runs.per.week", "data_type": "numeric", "nominal_values": null, "number_missing_values": 0}, {"index": 3, "name": "Age", "data_type": "numeric", "nominal_values": null, "number_missing_values": 0}, {"index": 4, "name": "Income", "data_type": "numeric", "nominal_values": null, "number_missing_values": 14}, {"index": 5, "name": "College", "data_type": "nominal", "nominal_values": ["0", "1"], "number_missing_values": 0}, {"index": 6, "name": "Distance", "data_type": "nominal", "nominal_values": ["0", "1"], "number_missing_values": 0}, {"index": 7, "name": "Treadmill", "data_type": "nominal", "nominal_values": ["0", "1"], "number_missing_values": 0}, {"index": 8, "name": "Miles.per.week", "data_type": "numeric", "nominal_values": null, "number_missing_values": 0}, {"index": 9, "name": "Type.of.running", "data_type": "nominal", "nominal_values": ["1Marathon", "2Half_marathon", "3Treadmill", "4Just_for_fun", "5Other"], "number_missing_values": 0}, {"index": 10, "name": "binaryClass", "data_type": "nominal", "nominal_values": ["N", "P"], "number_missing_values": 0}], "qualities": {"AutoCorrelation": 0.5423728813559322, "CfsSubsetEval_DecisionStumpAUC": 0.6070601851851852, "CfsSubsetEval_DecisionStumpErrRate": 0.38333333333333336, "CfsSubsetEval_DecisionStumpKappa": 0.14814814814814814, "CfsSubsetEval_NaiveBayesAUC": 0.6070601851851852, "CfsSubsetEval_NaiveBayesErrRate": 0.38333333333333336, "CfsSubsetEval_NaiveBayesKappa": 0.14814814814814814, "CfsSubsetEval_kNN1NAUC": 0.6070601851851852, "CfsSubsetEval_kNN1NErrRate": 0.38333333333333336, "CfsSubsetEval_kNN1NKappa": 0.14814814814814814, "ClassEntropy": 0.9709505944546686, "DecisionStumpAUC": 0.6805555555555556, "DecisionStumpErrRate": 0.35, "DecisionStumpKappa": 0.29530201342281887, "Dimensionality": 0.18333333333333332, "EquivalentNumberOfAtts": 22.162766944414287, "J48.00001.AUC": 0.6440972222222221, "J48.00001.ErrRate": 0.38333333333333336, "J48.00001.Kappa": 0.1843971631205674, "J48.0001.AUC": 0.6440972222222221, "J48.0001.ErrRate": 0.38333333333333336, "J48.0001.Kappa": 0.1843971631205674, "J48.001.AUC": 0.6440972222222221, "J48.001.ErrRate": 0.38333333333333336, "J48.001.Kappa": 0.1843971631205674, "MajorityClassPercentage": 60.0, "MajorityClassSize": 36.0, "MaxAttributeEntropy": 1.444582984182719, "MaxKurtosisOfNumericAtts": 0.04855356849650505, "MaxMeansOfNumericAtts": 55.326086956521735, "MaxMutualInformation": 0.16634761669336, "MaxNominalAttDistinctValues": 5.0, "MaxSkewnessOfNumericAtts": 0.9452952390524099, "MaxStdDevOfNumericAtts": 26.965042676955818, "MeanAttributeEntropy": 0.8530814531800348, "MeanKurtosisOfNumericAtts": -0.4551935802432564, "MeanMeansOfNumericAtts": 28.7969384057971, "MeanMutualInformation": 0.04380998983068667, "MeanNoiseToSignalRatio": 18.472304295822838, "MeanNominalAttDistinctValues": 2.4285714285714284, "MeanSkewnessOfNumericAtts": 0.29728994399301034, "MeanStdDevOfNumericAtts": 13.019048843030202, "MinAttributeEntropy": 0.35335933502142136, "MinKurtosisOfNumericAtts": -0.9104567558297245, "MinMeansOfNumericAtts": 4.983333333333333, "MinMutualInformation": 0.00068638496783, "MinNominalAttDistinctValues": 2.0, "MinSkewnessOfNumericAtts": -0.40384531849392635, "MinStdDevOfNumericAtts": 1.295254266860067, "MinorityClassPercentage": 40.0, "MinorityClassSize": 24.0, "NaiveBayesAUC": 0.7598379629629629, "NaiveBayesErrRate": 0.3, "NaiveBayesKappa": 0.3749999999999999, "NumberOfBinaryFeatures": 6.0, "NumberOfClasses": 2.0, "NumberOfFeatures": 11.0, "NumberOfInstances": 60.0, "NumberOfInstancesWithMissingValues": 14.0, "NumberOfMissingValues": 14.0, "NumberOfNumericFeatures": 4.0, "NumberOfSymbolicFeatures": 7.0, "PercentageOfBinaryFeatures": 54.54545454545454, "PercentageOfInstancesWithMissingValues": 23.333333333333332, "PercentageOfMissingValues": 2.1212121212121215, "PercentageOfNumericFeatures": 36.36363636363637, "PercentageOfSymbolicFeatures": 63.63636363636363, "Quartile1AttributeEntropy": 0.5457200622926557, "Quartile1KurtosisOfNumericAtts": -0.813383256972528, "Quartile1MeansOfNumericAtts": 9.915416666666665, "Quartile1MutualInformation": 0.002068690056365, "Quartile1SkewnessOfNumericAtts": -0.2529116950425616, "Quartile1StdDevOfNumericAtts": 3.3380815052874295, "Quartile2AttributeEntropy": 0.8589658205859301, "Quartile2KurtosisOfNumericAtts": -0.47943556681990307, "Quartile2MeansOfNumericAtts": 27.439166666666665, "Quartile2MutualInformation": 0.020946072373845, "Quartile2SkewnessOfNumericAtts": 0.32385492770677893, "Quartile2StdDevOfNumericAtts": 11.90794921415246, "Quartile3AttributeEntropy": 1.105726586536536, "Quartile3KurtosisOfNumericAtts": -0.07276191693733813, "Quartile3MeansOfNumericAtts": 49.03623188405797, "Quartile3MutualInformation": 0.0801401547903625, "Quartile3SkewnessOfNumericAtts": 0.8209265993148137, "Quartile3StdDevOfNumericAtts": 23.811115809650715, "REPTreeDepth1AUC": 0.7048611111111112, "REPTreeDepth1ErrRate": 0.35, "REPTreeDepth1Kappa": 0.32258064516129037, "REPTreeDepth2AUC": 0.7048611111111112, "REPTreeDepth2ErrRate": 0.35, "REPTreeDepth2Kappa": 0.32258064516129037, "REPTreeDepth3AUC": 0.7048611111111112, "REPTreeDepth3ErrRate": 0.35, "REPTreeDepth3Kappa": 0.32258064516129037, "RandomTreeDepth1AUC": 0.6475694444444444, "RandomTreeDepth1ErrRate": 0.35, "RandomTreeDepth1Kappa": 0.2657342657342658, "RandomTreeDepth2AUC": 0.6475694444444444, "RandomTreeDepth2ErrRate": 0.35, "RandomTreeDepth2Kappa": 0.2657342657342658, "RandomTreeDepth3AUC": 0.6475694444444444, "RandomTreeDepth3ErrRate": 0.35, "RandomTreeDepth3Kappa": 0.2657342657342658, "StdvNominalAttDistinctValues": 1.1338934190276817, "kNN1NAUC": 0.5625, "kNN1NErrRate": 0.43333333333333335, "kNN1NKappa": 0.12162162162162152}}